ECSFooPkg/__init__.py
ECSFooPkg/accessor.py
ECSFooPkg/plugins.py
ECSFooPkg-0.0.2.dist-info/METADATA
ECSFooPkg-0.0.2.dist-info/WHEEL
ECSFooPkg-0.0.2.dist-info/entry_points.txt
ECSFooPkg-0.0.2.dist-info/top_level.txt
ECSFooPkg-0.0.2.dist-info/RECORD
