Metadata-Version: 2.1
Name: ECSFooPkg
Version: 0.0.2
Summary: A dummy template of a python package with tests and documentation.
Author-email: Oriol Tintó <oriol.tinto@lmu.de>
Project-URL: Homepage, https://gitlab.physik.uni-muenchen.de/LDAP_meteo/ECS_Foo
Project-URL: Bug Tracker, https://gitlab.physik.uni-muenchen.de/LDAP_meteo/ECS_Foo/-/issues
Classifier: Programming Language :: Python :: 3
Classifier: License :: OSI Approved :: MIT License
Classifier: Operating System :: OS Independent
Requires-Python: >=3.7
Requires-Dist: enstools-encoding (>=2022.12)
Requires-Dist: xarray
Requires-Dist: hdf5plugin
Requires-Dist: pooch
Requires-Dist: netCDF4
